Metadata-Version: 2.1
Name: diana-calc
Version: 0.0.4
Summary: A very basic calculator
Home-page: UNKNOWN
Author: Diana Lavrinovich
Author-email: dianalavrichek2008@gmail.com
License: UNKNOWN
Keywords: calculator
Platform: UNKNOWN
Classifier: Development Status :: 5 - Production/Stable
Classifier: Intended Audience :: Education
Classifier: Operating System :: Microsoft :: Windows :: Windows 10
Classifier: License :: OSI Approved :: MIT License
Classifier: Programming Language :: Python :: 3
License-File: LICENCE.txt
